eknowledge/__init__.py
eknowledge/main.py
eknowledge/prompts.py
eknowledge/relations.py
eknowledge-2025.5.21720.dist-info/licenses/LICENSE
tests/__init__.py
tests/test_eknowledge.py
eknowledge-2025.5.21720.dist-info/METADATA
eknowledge-2025.5.21720.dist-info/WHEEL
eknowledge-2025.5.21720.dist-info/top_level.txt
eknowledge-2025.5.21720.dist-info/RECORD
