Metadata-Version: 2.4
Name: eknowledge
Version: 2025.5.21720
Summary: A Python package for executing graph generation from textual inputs.
Home-page: https://github.com/chigwell/eknowledge
Author: Eugene Evstafev
Author-email: chigwel@gmail.com
Classifier: License :: OSI Approved :: MIT License
Classifier: Development Status :: 3 - Alpha
Classifier: Intended Audience :: Developers
Classifier: Programming Language :: Python :: 3
Classifier: Operating System :: OS Independent
Requires-Python: >=3.6
License-File: LICENSE
Requires-Dist: langchain-core==0.3.51
Requires-Dist: langchain-ollama==0.3.0
Dynamic: author
Dynamic: author-email
Dynamic: classifier
Dynamic: description
Dynamic: description-content-type
Dynamic: home-page
Dynamic: license-file
Dynamic: requires-dist
Dynamic: requires-python
Dynamic: summary
